{
    "unfinished": [
        {
            "name": "vivy",
            "search_keywords":"[NC-Raws] Vivy －Fluorite Eye's Song [Baha][WEB-DL][1080p][AVC AAC][CHT][MP4]",
            "match_keywords": ["[NC-Raws]","[Vivy]","[Baha]","[WEB-DL]","[1080p]","[AVC AAC]","[CHT]","[MP4]"]
        },
        {
            "name": "异世界魔王与召唤少女的奴隶魔术Ω",
            "search_keywords":"[c.c動漫][4月新番][異世界魔王與召喚少女的奴隸魔術Ω][BIG5][1080P][MP4]",
            "match_keywords": ["[c.c動漫]","[4月新番]","[異世界魔王與召喚少女的奴隸魔術Ω]","[BIG5]","[1080P]","[MP4]"]
        },
        {
            "name": "战斗员派遣中",
            "search_keywords": "【幻樱字幕组】【4月新番】【战斗员派遣中！ Sentouin, Hakenshimasu!】【GB_MP4】【1920X1080】",
            "match_keywords":["【幻樱字幕组】","【4月新番】","【战斗员派遣中！ Sentouin, Hakenshimasu!】","【GB_MP4】","【1920X1080】"]
        }
    ]
}